[
  {
    "name": "790-oji daugiabučio namo savininkų bendrija",
    "code": "125617996",
    "address": "Vilnius, Pylimo g. 42-1"
  },
  {
    "name": "791-oji daugiabučio namo savininkų bendrija",
    "code": "125618030",
    "address": "Vilniaus m. sav., Grigiškių m., Vilniaus g. 4, LT-27101"
  },
  {
    "name": "793-oji gyvenamojo namo statybos bendrija",
    "code": "125618379",
    "address": "Vilnius, V. Grybo g. 19, LT-10318"
  },
  {
    "name": "794-oji daugiabučio namo savininkų bendrija",
    "code": "125618411",
    "address": "Vilnius, Smėlio g. 23-41, LT-10323"
  },
  {
    "name": "795-oji daugiabučio namo savininkų bendrija",
    "code": "125618564",
    "address": "Vilniaus m. sav., Grigiškių m., Jaunimo skg. 2, LT-27107"
  },
  {
    "name": "796-oji daugiabučio namo savininkų bendrija",
    "code": "225618750",
    "address": "Vilnius, Kareivių g. 9-120, LT-09108"
  },
  {
    "name": "797-oji daugiabučio namo savininkų bendrija",
    "code": "125618945",
    "address": "Vilnius, Jono Kazlausko g. 28-3, LT-08247"
  },
  {
    "name": "799-oji daugiabučio namo savininkų bendrija \"JAUNYSTĖ\"",
    "code": "181606843",
    "address": "Vilniaus m. sav., Grigiškių m., Šviesos g. 14-81, LT-27123"
  },
  {
    "name": "260-oji daugiabučio gyvenamojo namo Žirmūnų g. 79 savininkų bendrija \"Planeta\"",
    "code": "124798942",
    "address": "Vilnius, Žirmūnų g. 79-29, LT-09112"
  },
  {
    "name": "57-oji garažų eksploatavimo bendrija Dvaro g. 79",
    "code": "145592931",
    "address": "Šiauliai, Dvaro g. 79, LT-76299"
  },
  {
    "name": "79-oji butų savininkų bendrija",
    "code": "135407786",
    "address": "Kaunas, Lelijų g. 4, LT-44163"
  },
  {
    "name": "79-oji daugiabučio namo savininkų bendrija",
    "code": "125112613",
    "address": "Vilnius, Vydūno g. 18-9, LT-06205"
  },
  {
    "name": "79-oji garažų eksploatavimo bendrija Garažų g.",
    "code": "145593129",
    "address": "Šiauliai, Garažų g."
  },
  {
    "name": "79-oji garažų statybos ir eksploatavimo bendrija",
    "code": "135395241",
    "address": "Kaunas, V. Krėvės pr. 53A, LT-50358"
  },
  {
    "name": "Daugiabučio namo Dvaro g. 79 savininkų bendrija",
    "code": "145505353",
    "address": "Šiauliai, Dvaro g. 79, LT-76299"
  },
  {
    "name": "J. Basanavičiaus 79 namo savininkų bendrija",
    "code": "161754083",
    "address": "Kėdainiai, J. Basanavičiaus g. 79, LT-57279"
  },
  {
    "name": "Kniaudiškių g. 79-ojo namo savininkų bendrija",
    "code": "305608543",
    "address": "Panevėžys, Kniaudiškių g. 79-31, LT-37128"
  },
  {
    "name": "Staniūnų g. 79-ojo namo savininkų bendrija",
    "code": "148296072",
    "address": "Panevėžys, Staniūnų g. 79, LT-36152"
  },
  {
    "name": "UAB 79DOMOV",
    "code": "305590287",
    "address": "Vilniaus miesto savivaldybės teritorija"
  }
]