[
  {
    "name": "820-oji daugiabučio namo savininkų bendrija",
    "code": "125797448",
    "address": "Vilnius, Keramikų g. 100-18, LT-10255"
  },
  {
    "name": "821-oji daugiabučio namo savininkų bendrija",
    "code": "125797590",
    "address": "Vilnius, Sakalų g. 6-36, LT-08124"
  },
  {
    "name": "824-oji daugiabučio namo savininkų bendrija",
    "code": "125798016",
    "address": "Vilnius, Kalvarijų g. 294D-55, LT-08318"
  },
  {
    "name": "826-oji daugiabučio namo savininkų bendrija",
    "code": "125798354",
    "address": "Vilnius, Bitėnų g. 10-23, LT-06227"
  },
  {
    "name": "827-oji daugiabučio namo savininkų bendrija",
    "code": "225798540",
    "address": "Vilnius, M. Počobuto g. 2-7, LT-10228"
  },
  {
    "name": "829-oji daugiabučio namo savininkų bendrija",
    "code": "125800271",
    "address": "Vilnius, Architektų g. 60A-21, LT-04110"
  },
  {
    "name": "82-oji garažų statybos ir eksploatavimo bendrija",
    "code": "148311250",
    "address": "Panevėžys, Ateities g. 17, LT-37341"
  },
  {
    "name": "Aukštaičių g. 82-ojo namo savininkų bendrija",
    "code": "148291716",
    "address": "Panevėžys, Aukštaičių g. 82, LT-36115"
  },
  {
    "name": "DNSB \"Sukilėlių 82\"",
    "code": "301530595",
    "address": "Kaunas, Sukilėlių pr. 82-32, LT-49336"
  },
  {
    "name": "Daugiabučio namo savininkų bendrija Gegužių g. 82",
    "code": "145597145",
    "address": "Šiauliai, Gegužių g. 82, LT-78364"
  },
  {
    "name": "Daugiabučio namo savininkų bendrija Likiškėlių g. 82",
    "code": "150017918",
    "address": "Alytus, Likiškėlių g. 82, LT-63358"
  },
  {
    "name": "Molainių g. 78-ojo, 80-ojo, 82-ojo namų savininkų bendrija",
    "code": "148457013",
    "address": "Panevėžys, Molainių g. 80, LT-37151"
  },
  {
    "name": "Namo bendrija Basanavičiaus 82",
    "code": "161598531",
    "address": "Kėdainiai, J. Basanavičiaus g. 82, LT-57362"
  },
  {
    "name": "Ramygalos g. 82-ojo namo savininkų bendrija",
    "code": "148295928",
    "address": "Panevėžys, Ramygalos g. 82, LT-36228"
  },
  {
    "name": "Staniūnų 82-ojo daugiabučio gyvenamojo namo savininkų bendrija",
    "code": "302467144",
    "address": "Panevėžys, Staniūnų g. 82-33, LT-36158"
  }
]