[
  {
    "name": "UAB ATORA FISHING",
    "code": "305706286",
    "address": "Panevėžys, Sirupio g. 49-43, LT-36208",
    "vatcode": "LT100013857614"
  },
  {
    "name": "UAB \"ATORAS\"",
    "code": "301804530",
    "address": "Šiauliai, K. Korsako g. 53-43, LT-78371"
  },
  {
    "name": "UAB \"ATOREX\"",
    "code": "302341341",
    "address": "Šiauliai, Daubos g. 7-5, LT-78150",
    "vatcode": "LT100005696518"
  },
  {
    "name": "UAB \"Atoria\"",
    "code": "304961768",
    "address": "Mažeikiai, Pramonės g. 27, LT-89214",
    "vatcode": "LT100012037815"
  },
  {
    "name": "UAB \"Atorsa\"",
    "code": "303130564",
    "address": "Šiaulių r. sav., Šiaulių kaimiškoji sen., Pailių k., Šventupio g. 11, LT-80183",
    "vatcode": "LT100008037813"
  }
]