[
  {
    "name": "Baiza Baltic, UAB",
    "code": "306256397",
    "address": "Vilnius, Elbingo g. 83-20, LT-06285",
    "vatcode": "LT100015831914"
  },
  {
    "name": "MB \"Baiza\"",
    "code": "305701620",
    "address": "Vilnius, Priegliaus g. 10-30, LT-06288",
    "vatcode": "LT100013809816"
  },
  {
    "name": "UAB Baiza food",
    "code": "306686228",
    "address": "Vilnius, Švyturio g. 19-55, LT-10212",
    "vatcode": "LT100016760311"
  },
  {
    "name": "UAB Baiza meal",
    "code": "306717360",
    "address": "Šalčininkų r. sav., Jašiūnų sen., Rūdninkų k., Bažnyčios g. 50, LT-17237",
    "vatcode": "LT100016913615"
  }
]