[
  {
    "name": "CS Payments UAB",
    "code": "306320736",
    "address": "Vilnius, Gedimino pr. 44A-201, LT-01110"
  },
  {
    "name": "MB \"Star cs\"",
    "code": "306698426",
    "address": "Kauno r. sav., Karmėlavos sen., Ramučių k., Centrinė g. 2, LT-54464"
  },
  {
    "name": "PRO. MED. CS PRAHA A.S. ATSTOVYBĖ",
    "code": "111903336",
    "address": "Vilnius, Lukiškių g. 5-206"
  },
  {
    "name": "PRO.MED.CS Baltic, UAB",
    "code": "303012256",
    "address": "Vilnius, Lukiškių g. 5, LT-01108",
    "vatcode": "LT100007626518"
  },
  {
    "name": "Telia CS LT darbuotojų profesinė sąjunga",
    "code": "304158901",
    "address": "Panevėžys, Respublikos g. 58, LT-35171"
  },
  {
    "name": "UAB \"CS Capital\"",
    "code": "306296089",
    "address": "Neringa, G. D. Kuverto g. 9-15, LT-93124"
  },
  {
    "name": "UAB \"CS Construction\"",
    "code": "302712992",
    "address": "Vilnius, Tuskulėnų g. 33C-41, LT-09219",
    "vatcode": "LT100013146110"
  },
  {
    "name": "UAB \"CS system\"",
    "code": "305577521",
    "address": "Panevėžys, Vilniaus g. 29, LT-36100"
  },
  {
    "name": "UAB NRD CS",
    "code": "303115085",
    "address": "Vilnius, Gynėjų g. 14, LT-01109",
    "vatcode": "LT100008214514"
  },
  {
    "name": "UAB \"Vengriško maisto ir gėrimų ambasados\" darbuotojų profesinė sąjunga \"Csarda\"",
    "code": "301171085",
    "address": "Vilnius, Šv. Mykolo g. 4-1, LT-01124"
  },
  {
    "name": "\"CSC Pharma\", UAB",
    "code": "304245516",
    "address": "Vilnius, Juozo Miltinio g. 30, LT-14270",
    "vatcode": "LT100010418611"
  },
  {
    "name": "CSC Crewing B.V. Lietuvos filialas",
    "code": "303280806",
    "address": "Klaipėda, Liepų g. 5, LT-92138"
  },
  {
    "name": "UAB \"CSC TELECOM\"",
    "code": "111818067",
    "address": "Vilnius, Perkūnkiemio g. 7, LT-12131",
    "vatcode": "LT118180610"
  },
  {
    "name": "CSD Ingenieure AG Lietuvos filialas",
    "code": "300828432",
    "address": "Vilnius, Olimpiečių g. 1A, LT-09235"
  },
  {
    "name": "CSD Ingenieurs SA filialas",
    "code": "305564278",
    "address": "Vilnius, Olimpiečių g. 1A, LT-09235"
  },
  {
    "name": "CSD Inžinieriai, UAB",
    "code": "302838083",
    "address": "Vilnius, Olimpiečių g. 1A, LT-09235",
    "vatcode": "LT100008259211"
  },
  {
    "name": "Nasdaq CSD SE Lietuvos filialas",
    "code": "304602060",
    "address": "Vilnius, Konstitucijos pr. 29-1, LT-08105"
  },
  {
    "name": "MB \"CSE Team\"",
    "code": "306405282",
    "address": "Klaipėdos r. sav., Sendvario sen., Slengių k., Pavandenės g. 23, LT-92338",
    "vatcode": "LT100016366012"
  },
  {
    "name": "UAB \"CSG IT\"",
    "code": "304875924",
    "address": "Vilnius, Ozo g. 12A-1, LT-08200",
    "vatcode": "LT100012074517"
  },
  {
    "name": "VšĮ \"CSI Vilnius\"",
    "code": "302549538",
    "address": "Vilnius, Sakalų g. 22-52, LT-08108"
  },
  {
    "name": "UAB \"CSO Pharma Baltic\"",
    "code": "300543141",
    "address": "Vilnius, J. Galvydžio g. 5, LT-08236",
    "vatcode": "LT100002860816"
  },
  {
    "name": "VŠĮ CSO Fusion",
    "code": "306508097",
    "address": "Vilnius, Gabijos g. 43-11, LT-06100"
  },
  {
    "name": "MB Csolution",
    "code": "306658257",
    "address": "Zarasų r. sav., Salako sen., Nečeskų k. 2, LT-32210"
  },
  {
    "name": "UAB \"CSP\"",
    "code": "300145931",
    "address": "Klaipėda, S. Šimkaus g. 12-57, LT-92129",
    "vatcode": "LT100001924114"
  },
  {
    "name": "UAB CSSi LT",
    "code": "305691464",
    "address": "Vilnius, Laisvės pr. 125A, LT-06118"
  },
  {
    "name": "UAB \"CSUB LT\"",
    "code": "303289082",
    "address": "Klaipėda, Pilies g. 8, LT-91234",
    "vatcode": "LT100008518617"
  },
  {
    "name": "CSV GROUP, MB",
    "code": "306686826",
    "address": "Vilnius, Saltoniškių g. 12-2, LT-08126",
    "vatcode": "LT100016910217"
  },
  {
    "name": "MB Csvcamp",
    "code": "306315550",
    "address": "Vilnius, J. Savickio g. 4-7, LT-01108"
  },
  {
    "name": "CSX SOLUTIONS, UAB",
    "code": "305915745",
    "address": "Vilnius, J. Savickio g. 4-7, LT-01108"
  }
]