[
  {
    "name": "MB \"Dingas ir aš\"",
    "code": "305895591",
    "address": "Kaunas, Įkalnės aklg. 10-13, LT-47163"
  },
  {
    "name": "MB \"Dingom\"",
    "code": "303324455",
    "address": "Vilnius, Verkių g. 23-90, LT-08246"
  },
  {
    "name": "Dingusių žmonių šeimų paramos centras",
    "code": "191970496",
    "address": "Vilnius, I. Kanto al. 23-34, LT-06202"
  },
  {
    "name": "VšĮ \"Dingę kaimai\"",
    "code": "305930583",
    "address": "Ignalinos r. sav., Naujojo Daugėliškio sen., Degutiškės II k. 6, LT-30288"
  },
  {
    "name": "Viešoji įstaiga \"Dingęs Štetlas\" - Šeduvos žydų istorijos muziejus",
    "code": "303054853",
    "address": "Vilnius, Dominikonų g. 5, LT-01131",
    "vatcode": "LT100012834317"
  }
]