[
  {
    "name": "IĮ \"Tu esi grožis\"",
    "code": "305726762",
    "address": "Palanga, Vanagupės g. 24-71, LT-00172"
  },
  {
    "name": "Labdaros fondas Esi tu - esu ir aš",
    "code": "306713127",
    "address": "Kaunas, Rasytės g. 20-44, LT-48120"
  },
  {
    "name": "MB \"Esi LT\"",
    "code": "304460682",
    "address": "Kaunas, Partizanų g. 81D, LT-50310"
  },
  {
    "name": "MB \"Esi dovana\"",
    "code": "305548719",
    "address": "Vilnius, Kryžiokų Sodų 9-oji g. 78, LT-08445"
  },
  {
    "name": "VšĮ \"Ačiū, kad esi\"",
    "code": "304255827",
    "address": "Vilnius, Kalvarijų g. 300, LT-08318"
  },
  {
    "name": "VšĮ \"Tu esi Vilnius\"",
    "code": "305938936",
    "address": "Vilnius, Pušyno kel. 3A-3, LT-08311"
  },
  {
    "name": "Uždaroji akcinė bendrovė \"ESIDA\"",
    "code": "186443229",
    "address": "Vilnius, Žirnių g. 10, LT-02120",
    "vatcode": "LT864432219"
  },
  {
    "name": "Uždaroji akcinė bendrovė \"ESIGA\"",
    "code": "120736352",
    "address": "Vilnius, Eišiškių pl. 103-1",
    "vatcode": "LT207363515"
  },
  {
    "name": "MB ESIGDA",
    "code": "305683581",
    "address": "Alytaus r. sav., Alytaus sen., Norūnų k., Ramunių g. 3, LT-62193"
  },
  {
    "name": "UAB \"Esigna\"",
    "code": "148135788",
    "address": "Panevėžys, Medžiotojų g. 9, LT-37176",
    "vatcode": "LT481357811"
  },
  {
    "name": "MB \"Esigra\"",
    "code": "305732797",
    "address": "Kaunas, Vienybės g. 12, LT-51384"
  },
  {
    "name": "UAB \"Esila\"",
    "code": "305229447",
    "address": "Vilniaus r. sav., Nemėžio sen., Paliepių k., Lyglaukių g. 38, LT-13280",
    "vatcode": "LT100013274919"
  },
  {
    "name": "UAB \"Esim telecom\"",
    "code": "305695740",
    "address": "Vilnius, Verkių g. 23-65, LT-08246"
  },
  {
    "name": "UAB \"Esima\"",
    "code": "303569419",
    "address": "Šiauliai, Architektų g. 52-33, LT-78234",
    "vatcode": "LT100009197516"
  },
  {
    "name": "MB \"Esimas\"",
    "code": "304909166",
    "address": "Vilnius, Šiltnamių g. 42-44, LT-04128"
  },
  {
    "name": "UAB \"Esimeda\"",
    "code": "304517731",
    "address": "Telšiai, Masčio g. 38A-20, LT-87146",
    "vatcode": "LT100010895318"
  },
  {
    "name": "UAB \"Esimetrija\"",
    "code": "300574795",
    "address": "Kaunas, V. Krėvės pr. 72-13, LT-50395"
  },
  {
    "name": "MB \"Esinda LT\"",
    "code": "305616718",
    "address": "Vilnius, Girulių g. 5, LT-12124"
  },
  {
    "name": "UAB \"Esis LT\"",
    "code": "304738199",
    "address": "Kaunas, Ateities pl. 31, LT-52167",
    "vatcode": "LT100011516718"
  },
  {
    "name": "IĮ \"ESITA\"",
    "code": "302307517",
    "address": "Alytus, Šaltinių g. 5-40, LT-62347"
  },
  {
    "name": "UAB \"Esix\"",
    "code": "306398642",
    "address": "Kaunas, Partizanų g. 61-806, LT-49282"
  }
]