[
  {
    "name": "MB Gelu",
    "code": "305735238",
    "address": "Panevėžio r. sav., Ramygalos sen., Uliūnų k., Žalioji g. 40, LT-38241"
  },
  {
    "name": "Gelumbauskaitės įmonė",
    "code": "124296637",
    "address": "Vilnius, A. Vivulskio g. 3-6, LT-03162"
  },
  {
    "name": "Minijos Gelumbauskienės įmonė",
    "code": "135554850",
    "address": "Kaunas, Partizanų g. 16C-18, LT-50213"
  },
  {
    "name": "J. R. Adomaičio firma \"Gelumbė\"",
    "code": "151266331",
    "address": "Marijampolė, Klaipėdos g. 50, LT-68268"
  },
  {
    "name": "UAB \"Geluna\"",
    "code": "306379581",
    "address": "Lazdijai, Seinų g. 18-9, LT-67114"
  },
  {
    "name": "E. Gelusevičienės personalinė įmonė",
    "code": "123848680",
    "address": "Vilnius, Kapsų g. 22-45, LT-02166"
  },
  {
    "name": "UAB \"Gelusta\"",
    "code": "305175978",
    "address": "Vilnius, Girulių g. 5, LT-12124"
  },
  {
    "name": "S. Bernatavičiaus personali firma \"GELUVA\"",
    "code": "120408697",
    "address": "Vilnius, Žirmūnų g. 38-54, LT-09228"
  },
  {
    "name": "Sodininkų bendrija \"Geluvos sodai\"",
    "code": "301145585",
    "address": "Šiaulių r. sav., Bubių sen., Maskvytės k., Jurginų g. 32, LT-80163"
  }
]