[
  {
    "name": "Baltic sea groceries developments, UAB",
    "code": "306077184",
    "address": "Vilnius, J. Basanavičiaus g. 31-4, LT-03109"
  },
  {
    "name": "UAB Asian groceries",
    "code": "306761111",
    "address": "Vilnius, Šeškinės g. 6-65, LT-07152",
    "vatcode": "LT100017102513"
  },
  {
    "name": "MB \"Golden grocery and food store\"",
    "code": "306465240",
    "address": "Vilnius, Girulių g. 5, LT-12124"
  },
  {
    "name": "MB Afro grocery shop",
    "code": "306970029",
    "address": "Vilnius, Eduardo Andrė g. 14-5, LT-02232"
  },
  {
    "name": "V. Grockienės įmonė",
    "code": "132186770",
    "address": "Kaunas, A. Smetonos al. 55-30, LT-45315"
  },
  {
    "name": "MB Grockio vairavimo mokykla",
    "code": "304806860",
    "address": "Utena, Vaižganto g. 56-60, LT-28185",
    "vatcode": "LT100012408514"
  }
]