[
  {
    "name": "UAB \"JAGME\"",
    "code": "302861107",
    "address": "Šiauliai, Vilniaus g. 179A-8, LT-76350"
  },
  {
    "name": "Egidijaus Jagmino personalinė įmonė",
    "code": "181331849",
    "address": "Vilniaus m. sav., Grigiškės, Kunigiškių g. 14, LT-27109"
  },
  {
    "name": "Irmanto Jagmino UAB",
    "code": "171653385",
    "address": "Šiauliai, Vilniaus g. 179A-8, LT-76350",
    "vatcode": "LT716533811"
  },
  {
    "name": "Jono Jagmino vairuotojų rengimo įmonė",
    "code": "171464922",
    "address": "Radviliškis, Aušros a. 5-23, LT-82196"
  },
  {
    "name": "Mažeikių Kazimiero Jagmino pradinė mokykla",
    "code": "191814981",
    "address": "Mažeikiai, Sedos g. 12, LT-89233"
  },
  {
    "name": "Virginijaus Jagmino įmonė",
    "code": "145771471",
    "address": "Šiauliai, Vytauto g. 265-55, LT-77183"
  }
]