[
  {
    "name": "J. Sederevičiaus įmonė \"Joseda\"",
    "code": "172320241",
    "address": "Raseiniai, Maironio g. 4-1, LT-60169"
  },
  {
    "name": "KLUBAS \"JOSEDOS SPORTAS\"",
    "code": "302195534",
    "address": "Raseiniai, Maironio g. 4-1, LT-60169"
  },
  {
    "name": "MB \"Joselos transportas\"",
    "code": "304169876",
    "address": "Vilnius, Švitrigailos g. 7, LT-03110",
    "vatcode": "LT100010484811"
  },
  {
    "name": "UAB \"Josena\"",
    "code": "302881063",
    "address": "Elektrėnų sav., Elektrėnų sen., Geibonių k., Geibonių g. 11, LT-26135"
  },
  {
    "name": "UAB \"Joseta\"",
    "code": "303318452",
    "address": "Vilnius, Dūkštų g. 16-12, LT-07173"
  }
]