[
  {
    "name": "UAB KLAS",
    "code": "302595069",
    "address": "Vilnius, Ozo g. 12A, LT-08200"
  },
  {
    "name": "Uždaroji akcinė bendrovė \"KLASANA\"",
    "code": "140477099",
    "address": "Klaipėda, Šilutės pl. 23A, LT-95107",
    "vatcode": "LT404770917"
  },
  {
    "name": "UAB \"Klasauta\"",
    "code": "305186907",
    "address": "Šilutė, Tilžės g. 23-6, LT-99144",
    "vatcode": "LT100012437013"
  },
  {
    "name": "AB \"KLAIPĖDOS JŪRŲ KROVINIŲ KOMPANIJA\" filialas \"KLASCO SERVISAS\"",
    "code": "141908570",
    "address": "Klaipėda, Naujoji Uosto g. 23, LT-92245"
  },
  {
    "name": "Akcinės bendrovės Klaipėdos jūrų krovinių kompanijos filialas \"Klasco towage assistance\"",
    "code": "300076093",
    "address": "Klaipėda, Naujoji Uosto g. 23, LT-92245"
  },
  {
    "name": "Uždaroji akcinė bendrovė \"KLASERA\"",
    "code": "140544498",
    "address": "Klaipėda, Šilutės pl. 50, LT-94181",
    "vatcode": "LT405444917"
  },
  {
    "name": "UAB \"KLASETA\"",
    "code": "300547531",
    "address": "Šilutės r. sav., Šilutės sen., Pagrynių k., Šilutės g. 4B, LT-99159"
  },
  {
    "name": "Uždaroji akcinė bendrovė \"KLASFARMA\"",
    "code": "124573098",
    "address": "Vilnius, Algirdo g. 9A-6, LT-03161"
  },
  {
    "name": "Mažoji bendrija \"KLASIK\"",
    "code": "302886352",
    "address": "Mažeikiai, Naftininkų g. 30-31, LT-89132"
  },
  {
    "name": "Sporto klubas \"KLASIK\"",
    "code": "302324769",
    "address": "Tauragė, Dariaus ir Girėno g. 32-16, LT-72245"
  },
  {
    "name": "J. N. Grušeckaitės įmonė \"LAIKO KLASIKA\"",
    "code": "125301838",
    "address": "Vilnius, Stadiono g. 1-2, LT-02106"
  },
  {
    "name": "MB \"Batų klasika\"",
    "code": "303011097",
    "address": "Klaipėda, Varpų g. 14-21, LT-94271"
  },
  {
    "name": "MB \"Senoji klasika\"",
    "code": "306179584",
    "address": "Kaunas, Siūlų g. 5-1, LT-45196"
  },
  {
    "name": "MB \"Žaidimų klasika\"",
    "code": "304839974",
    "address": "Kaunas, Pakraščio g. 4-5, LT-49427"
  },
  {
    "name": "MB \"Žanro klasika\"",
    "code": "304726058",
    "address": "Druskininkai, Dabintos g. 11-5, LT-66111"
  },
  {
    "name": "MB Gastro klasika",
    "code": "306660913",
    "address": "Vilnius, A. Domaševičiaus g. 5-6, LT-01400"
  },
  {
    "name": "MB Naujoji klasika",
    "code": "306260075",
    "address": "Šiauliai, Architektų g. 26-38, LT-78279",
    "vatcode": "LT100016311419"
  },
  {
    "name": "Mažoji bendrija \"Dizaino klasika\"",
    "code": "305953735",
    "address": "Birštonas, Vytauto g. 2-5, LT-59211"
  },
  {
    "name": "Panevėžio automobilių sporto klubas \"KLASIKA\"",
    "code": "248241080",
    "address": "Panevėžys, S. Kerbedžio g. 34-3, LT-35110"
  },
  {
    "name": "Senovinių automobilių klubas \"Klasika\"",
    "code": "304895019",
    "address": "Biržų r. sav., Pačeriaukštės sen., Sodeliškių k., Lauko g. 2B, LT-41420"
  },
  {
    "name": "UAB \"Faber klasika\"",
    "code": "301560649",
    "address": "Marijampolės sav., Šunskai, Varpo g. 63A, LT-69360"
  },
  {
    "name": "UAB \"Kasdienė klasika\"",
    "code": "156565070",
    "address": "Jonava, Kauno g. 4, LT-55176"
  },
  {
    "name": "UAB \"Kompiuterių klasika\"",
    "code": "301118531",
    "address": "Panevėžys, Kosmonautų g. 5-49, LT-37357"
  },
  {
    "name": "UAB \"Moderni klasika\"",
    "code": "126223698",
    "address": "Vilnius, Šv. Stepono g. 9, LT-01139",
    "vatcode": "LT262236917"
  },
  {
    "name": "UAB \"Senamiesčio klasika\"",
    "code": "304166474",
    "address": "Telšiai, Respublikos g. 2-3, LT-87130",
    "vatcode": "LT100011022216"
  },
  {
    "name": "UAB Dn klasika",
    "code": "305819832",
    "address": "Panevėžys, Pievų g. 52, LT-37463"
  },
  {
    "name": "UAB dailės galerija \"Klasika\"",
    "code": "304072085",
    "address": "Vilnius, Savanorių pr. 11A-16, LT-03116",
    "vatcode": "LT100011734315"
  },
  {
    "name": "Uždaroji akcinė bendrovė \"Drabužių klasika\"",
    "code": "135225940",
    "address": "Kauno r. sav., Ringaudų sen., Ringaudų k., Rasos g. 19, LT-53331",
    "vatcode": "LT352259418"
  },
  {
    "name": "Uždaroji akcinė bendrovė \"Odos ir kailių klasika\"",
    "code": "126126879",
    "address": "Vilnius, Paupio g. 28, LT-11341"
  },
  {
    "name": "Uždaroji akcinė bendrovė \"UŽUPIO KLASIKA\"",
    "code": "125548436",
    "address": "Vilnius, Užupio g. 28-4, LT-01203"
  },
  {
    "name": "Viešoji įstaiga senovinės technikos klubas \"Klasika\"",
    "code": "302298694",
    "address": "Biržų r. sav., Širvėnos sen., Biržų k., Bokšto g. 18, LT-41180"
  },
  {
    "name": "Vilniaus rusų muzikos draugija \"Rusų klasika\"",
    "code": "191856756",
    "address": "Vilnius, Žygimantų g. 6, LT-01102"
  },
  {
    "name": "VšĮ \"Klasika LT\"",
    "code": "302857888",
    "address": "Vilnius, Šeimyniškių g. 42-20, LT-09213"
  },
  {
    "name": "UAB \"Klasikiniai baldai\"",
    "code": "300569346",
    "address": "Marijampolės sav., Šunskai, Parko g. 14, LT-69360"
  },
  {
    "name": "UAB \"Klasikiniai langai\"",
    "code": "303680871",
    "address": "Vilniaus r. sav., Nemenčinės sen., Eitminiškių k., Misionierių g. 7, LT-15131",
    "vatcode": "LT100011848412"
  },
  {
    "name": "Viešoji įstaiga \"Klasikiniai menai\"",
    "code": "304230489",
    "address": "Vilnius, Viršupio Sodų 4-oji g. 23, LT-10230"
  },
  {
    "name": "Vytauto Didžiojo universiteto klasikinio ugdymo mokykla",
    "code": "190134530",
    "address": "Kaunas, Vokiečių g. 164, LT-45299"
  },
  {
    "name": "MB \"Klasikinis kaljanas\"",
    "code": "305548936",
    "address": "Vilnius, V. Nagevičiaus g. 3, LT-08237"
  },
  {
    "name": "UŽDAROJI AKCINĖ BENDROVĖ \"KLASIKINIS FASONAS\"",
    "code": "125753284",
    "address": "Vilnius, Krokuvos g. 13, LT-09314",
    "vatcode": "LT257532811"
  },
  {
    "name": "Uždaroji akcinė bendrovė \"KLASIKINIS PORTIKAS\"",
    "code": "125139628",
    "address": "Vilnius, Bajorų Sodų 18-oji g. 27, LT-08426",
    "vatcode": "LT100002827410"
  },
  {
    "name": "Uždaroji akcinė bendrovė \"Klasikinis automobilis\"",
    "code": "235291820",
    "address": "Kaunas, Gebenių g. 71, LT-46326",
    "vatcode": "LT352918219"
  },
  {
    "name": "Uždaroji akcinė bendrovė \"Klasikinis stilius\"",
    "code": "141297773",
    "address": "Klaipėda, H. Manto g. 43, LT-92253",
    "vatcode": "LT412977716"
  },
  {
    "name": "LIETUVOS KLASIKINIŲ AUTOMOBILIŲ KLUBAS",
    "code": "195740140",
    "address": "Jonava, K. Donelaičio g. 2, LT-55189"
  },
  {
    "name": "MB \"Klasikinių automobilių servisas\"",
    "code": "304593387",
    "address": "Alytus, Vardos g. 85B, LT-62322",
    "vatcode": "LT100011063718"
  },
  {
    "name": "UAB \"KLASIKINIŲ AUTOMOBILIŲ KLUBAS\"",
    "code": "126306215",
    "address": "Vilnius, Vokiečių g. 18-7, LT-01130"
  },
  {
    "name": "A. R. Baumilų TŪB \"KLASIKINĖ TEKSTILĖ\"",
    "code": "147240238",
    "address": "Panevėžys, Staniūnų g. 83, LT-36151",
    "vatcode": "LT472402314"
  },
  {
    "name": "IĮ \"Klasikinė linija\"",
    "code": "300115062",
    "address": "Palanga, Medvalakio g. 9-7, LT-00141",
    "vatcode": "LT100002312017"
  },
  {
    "name": "R. Vaicekauskienės salonas \"KLASIKINĖ MADA\"",
    "code": "149716682",
    "address": "Alytus, Tvirtovės g. 16, LT-62116"
  },
  {
    "name": "Vilniaus Abraomo Kulviečio klasikinė gimnazija",
    "code": "195005870",
    "address": "Vilnius, Gedvydžių g. 8, LT-06306"
  },
  {
    "name": "Abraomo Kulviečio klasikinės gimnazijos labdaros ir paramos fondas",
    "code": "125534792",
    "address": "Vilnius, Laisvės pr. 125, LT-06118"
  },
  {
    "name": "Klasikinės gitaros mokytojų asociacija",
    "code": "300083547",
    "address": "Panevėžys, Vilniaus g. 2, LT-35208"
  },
  {
    "name": "Viešoji įstaiga \"Klasikinės Homeopatijos Centras\"",
    "code": "301737747",
    "address": "Vilniaus r. sav., Nemenčinės sen., Raudondvario k."
  },
  {
    "name": "VšĮ \"Indijos klasikinės muzikos klubas\"",
    "code": "306144569",
    "address": "Vilnius, Vytauto g. 44A-2, LT-08122"
  },
  {
    "name": "\"Klasikos degustacija\", UAB",
    "code": "304445246",
    "address": "Vilnius, Mindaugo g. 27-28, LT-03210",
    "vatcode": "LT100015506914"
  },
  {
    "name": "\"Klasikos koncertai\", VšĮ",
    "code": "304230820",
    "address": "Vilnius, Mindaugo g. 27-28, LT-03210"
  },
  {
    "name": "Klasikos pasaulio paramos fondas",
    "code": "305391424",
    "address": "Vilniaus r. sav., Avižienių sen., Raisteniškių vs., Raisteniškių g. 8, LT-14180"
  },
  {
    "name": "MB \"Klasikos pasaulis\"",
    "code": "305232589",
    "address": "Vilniaus r. sav., Avižienių sen., Raisteniškių vs., Raisteniškių g. 8, LT-14180"
  },
  {
    "name": "MB \"Klasikos perlas\"",
    "code": "305077480",
    "address": "Varėna, Dzūkų g. 62-5, LT-65167"
  },
  {
    "name": "MB \"Modernios klasikos laboratorija\"",
    "code": "304219293",
    "address": "Kaunas, Kaimelės g. 152, LT-47246"
  },
  {
    "name": "VšĮ \"Klasikos projektai\"",
    "code": "304172160",
    "address": "Vilkaviškio r. sav., Bartninkų sen., Vinkšnupių k. 1-1, LT-70334"
  },
  {
    "name": "VšĮ \"Klasikos šedevrai\"",
    "code": "303134146",
    "address": "Vilnius, Švitrigailos g. 11C, LT-03228"
  },
  {
    "name": "Klasikų Asociacija (Societas Classica)",
    "code": "300818438",
    "address": "Vilnius, Universiteto g. 5, LT-01131"
  },
  {
    "name": "Virgilijaus Klasinsko individuali įmonė",
    "code": "173747189",
    "address": "Rokiškis, Taikos g. 9A-55, LT-42143"
  },
  {
    "name": "Asociacija \"Klasiokai\"",
    "code": "304229298",
    "address": "Kaišiadorys, Gedimino g. 129-30, LT-56147"
  },
  {
    "name": "UAB \"KlasJet\"",
    "code": "303163347",
    "address": "Vilnius, Dariaus ir Girėno g. 34F, LT-02188",
    "vatcode": "LT100008090113"
  },
  {
    "name": "UAB \"Klasmann-Deilmann SRC Holding LT\"",
    "code": "303100382",
    "address": "Šilutės r. sav., Šilutės sen., Traksėdžių k., Šilojų g. 2, LT-99106",
    "vatcode": "LT100008053411"
  },
  {
    "name": "UAB \"Klasmann-Deilmann SRC Katyčiai\"",
    "code": "303126847",
    "address": "Šilutės r. sav., Šilutės sen., Traksėdžių k., Šilojų g. 2, LT-99106"
  },
  {
    "name": "UAB \"Klasmann-Deilmann SRC Kunigiškiai\"",
    "code": "303126929",
    "address": "Šilutės r. sav., Šilutės sen., Traksėdžių k., Šilojų g. 2, LT-99106"
  },
  {
    "name": "UAB \"Klasmann-Deilmann SRC Mažonai\"",
    "code": "303126733",
    "address": "Šilutės r. sav., Šilutės sen., Traksėdžių k., Šilojų g. 2, LT-99106"
  },
  {
    "name": "UAB \"Klasmann-Deilmann SRC Usėnai\"",
    "code": "303127618",
    "address": "Šilutės r. sav., Šilutės sen., Traksėdžių k., Šilojų g. 2, LT-99106"
  },
  {
    "name": "UAB \"Klasmann-Deilmann SRC Vakarai\"",
    "code": "303126719",
    "address": "Šilutės r. sav., Šilutės sen., Traksėdžių k., Šilojų g. 2, LT-99106"
  },
  {
    "name": "UAB \"Klasmann-Deilmann SRC Šilutė\"",
    "code": "303126797",
    "address": "Šilutės r. sav., Šilutės sen., Traksėdžių k., Šilojų g. 2, LT-99106"
  },
  {
    "name": "UAB Klasmann-Deilmann Bioenergy",
    "code": "142148298",
    "address": "Šilutės r. sav., Šilutės sen., Traksėdžių k., Šilojų g. 2, LT-99106",
    "vatcode": "LT421482917"
  },
  {
    "name": "UAB Klasmann-Deilmann Ežerėlis",
    "code": "136037197",
    "address": "Kauno r. sav., Ežerėlis, Kauno g. 17, LT-53387",
    "vatcode": "LT360371917"
  },
  {
    "name": "UAB Klasmann-Deilmann Laukėsa",
    "code": "210612720",
    "address": "Tauragės r. sav., Gaurės sen., Eičių k.",
    "vatcode": "LT106127219"
  },
  {
    "name": "UAB Klasmann-Deilmann Verdenis",
    "code": "300153860",
    "address": "Šilutės r. sav., Šilutės sen., Traksėdžių k., Šilojų g. 2, LT-99106",
    "vatcode": "LT100002957610"
  },
  {
    "name": "UAB Klasmann-Deilmann Šilutė",
    "code": "177209437",
    "address": "Šilutės r. sav., Šilutės sen., Traksėdžių k., Šilojų g. 2, LT-99106",
    "vatcode": "LT772094314"
  },
  {
    "name": "UAB \"Klastata\"",
    "code": "303014969",
    "address": "Klaipėdos r. sav., Sendvario sen., Klemiškės II k., Aukštagirių g. 1, LT-91287",
    "vatcode": "LT100007633319"
  },
  {
    "name": "Asociacija \"Anykščių turizmo klasteris\"",
    "code": "303140658",
    "address": "Anykščiai, Liudiškių g. 18, LT-29130"
  },
  {
    "name": "Asociacija \"Biržų turizmo klasteris\"",
    "code": "302976942",
    "address": "Biržai, J. Janonio g. 2, LT-41148"
  },
  {
    "name": "Asociacija \"Energiškai efektyvių ir pasyvių namų klasteris\"",
    "code": "303504439",
    "address": "Kretinga, Tiekėjų g. 23D, LT-97123"
  },
  {
    "name": "Asociacija \"Ignalinos turizmo klasteris\"",
    "code": "303575386",
    "address": "Ignalina, Ateities g. 23, LT-30121"
  },
  {
    "name": "Asociacija \"Nacionalinis maisto ūkio klasteris\"",
    "code": "300558951",
    "address": "Kauno r. sav., Babtai, Kauno g. 30, LT-54333"
  },
  {
    "name": "Asociacija \"Pamario turizmo klasteris\"",
    "code": "303695859",
    "address": "Klaipėdos r. sav., Priekulės sen., Drevernos k., Žvejų g. 13, LT-96240"
  },
  {
    "name": "Asociacija \"Telšių turizmo klasteris\"",
    "code": "305174506",
    "address": "Telšiai, Sedos g. 34A, LT-87101"
  },
  {
    "name": "Asociacija \"Žemaitijos turizmo klasteris\"",
    "code": "303287366",
    "address": "Plungės r. sav., Babrungo sen., Babrungėnų k., Malūno g. 11, LT-90110"
  },
  {
    "name": "Asociacija \"Žuvininkystės klasteris\"",
    "code": "303048708",
    "address": "Tauragė, Pramonės g. 28B, LT-72318"
  },
  {
    "name": "Asociacija Baltijos automobilių detalių klasteris",
    "code": "303280368",
    "address": "Kaunas, Jonavos g. 68A, LT-44191",
    "vatcode": "LT100008996614"
  },
  {
    "name": "Baltijos baldų klasteris",
    "code": "304214531",
    "address": "Šiaulių r. sav., Šiaulių kaimiškoji sen., Aukštelkės k., Sodybų g. 8, LT-80181"
  },
  {
    "name": "Energetikos klasteris, UAB",
    "code": "303097826",
    "address": "Kaunas, S. Daukanto g. 11A, LT-44305",
    "vatcode": "LT100007953413"
  },
  {
    "name": "Klasteris \"Panemunių turai\"",
    "code": "303509856",
    "address": "Jurbarko r. sav., Skirsnemunės sen., Kartupėnų k., Plento g. 4, LT-74462",
    "vatcode": "LT100012510215"
  },
  {
    "name": "LIETUVOS BALDŲ KLASTERIS",
    "code": "302506070",
    "address": "Vilnius, Pramonės g. 97-401, LT-11115"
  },
  {
    "name": "Lietuvos jūrinis klasteris",
    "code": "305637922",
    "address": "Klaipėda, Vilhelmo Berbomo g. 10, LT-92221"
  },
  {
    "name": "Lietuvos medicinos turizmo klasteris",
    "code": "303075979",
    "address": "Vilnius, Pamėnkalnio g. 40-1, LT-01114"
  },
  {
    "name": "Lietuvos socialinių inovacijų klasteris",
    "code": "305613437",
    "address": "Vilnius, Augustijonų g. 4, LT-01127"
  },
  {
    "name": "Mažoji bendrija \"JŪRINIS KLASTERIS\"",
    "code": "302887080",
    "address": "Klaipėda, Klaipėdos g. 8-16, LT-92354",
    "vatcode": "LT100009146313"
  },
  {
    "name": "Naujos kartos mokslo ir verslo klasteris",
    "code": "302336440",
    "address": "Klaipėda, Nemuno g. 2, LT-91199"
  },
  {
    "name": "Nebulos klasteris",
    "code": "303254252",
    "address": "Vilnius, Šeimyniškių g. 5-114, LT-09312"
  },
  {
    "name": "Regioninių medijų klasteris",
    "code": "306055736",
    "address": "Vilnius, Liudviko Zamenhofo g. 10-22, LT-06330"
  },
  {
    "name": "Santaka klasteris",
    "code": "305481430",
    "address": "Kaunas, T. Kosciuškos g. 27, LT-45462"
  },
  {
    "name": "Unikalių namų klasteris",
    "code": "306081841",
    "address": "Šiaulių r. sav., Meškuičių sen., Domantų k., Kulpės g. 2, LT-81439",
    "vatcode": "LT100016676116"
  },
  {
    "name": "Vladimir Uss individuali įmonė \"KLASTERIS\"",
    "code": "221850790",
    "address": "Vilnius, Rolando Jankausko g. 13-120, LT-04314"
  },
  {
    "name": "VšĮ \"AVA klasteris\"",
    "code": "305527333",
    "address": "Alytus, S. Dariaus ir S. Girėno g. 4A-2, LT-62137"
  },
  {
    "name": "VšĮ \"Sveikatos technologijų klasteris iVita\"",
    "code": "306716995",
    "address": "Kaunas, Gedimino g. 22A-14, LT-44319"
  },
  {
    "name": "VšĮ \"Ventos regioninis klasteris\"",
    "code": "305738017",
    "address": "Akmenės r. sav., Papilė, J. Basanavičiaus g. 19A-4, LT-85243"
  },
  {
    "name": "Asociacija Lietuvos klasterių tinklas",
    "code": "305560002",
    "address": "Vilnius, Mokslininkų g. 2A, LT-08412"
  },
  {
    "name": "Lietuvos klasterių asociacija",
    "code": "303419106",
    "address": "Vilnius, Olimpiečių g. 5-7, LT-09237"
  },
  {
    "name": "MB \"Klasvika\"",
    "code": "306049199",
    "address": "Vilnius, Santariškių g. 75-34, LT-08457"
  },
  {
    "name": "Asociacija \"Mūsų klasė\"",
    "code": "306680093",
    "address": "Kaišiadorys, Gedimino g. 127-45, LT-56147"
  },
  {
    "name": "IĮ vairavimo mokykla \"A klasė\"",
    "code": "304216920",
    "address": "Klaipėdos r. sav., Sendvario sen., Gindulių k., Žalioji g. 10-18, LT-91276"
  },
  {
    "name": "MB \"3D klasė\"",
    "code": "306660525",
    "address": "Vilniaus r. sav., Sudervės sen., Rastinėnų k., Užuovėjos 3-ioji g. 10, LT-14218"
  },
  {
    "name": "MB \"Energijos klasė\"",
    "code": "305705234",
    "address": "Kaunas, Baltijos g. 2-21, LT-48255",
    "vatcode": "LT100015124311"
  },
  {
    "name": "MB \"Finansų klasė\"",
    "code": "305405518",
    "address": "Vilkaviškis, Šiaurės g. 44, LT-70150",
    "vatcode": "LT100013548616"
  },
  {
    "name": "MB \"Komforto klasė\"",
    "code": "304788234",
    "address": "Vilnius, Baltupio g. 59-20, LT-08322"
  },
  {
    "name": "MB \"Mūro klasė\"",
    "code": "305655913",
    "address": "Vilnius, Gabijos g. 77-56, LT-06104"
  },
  {
    "name": "MB \"Top klasė\"",
    "code": "306186792",
    "address": "Kaunas, Europos pr. 34-47, LT-46370"
  },
  {
    "name": "MB Ligitos klasė",
    "code": "306313147",
    "address": "Kaunas, Tunelio g. 43-22, LT-51419"
  },
  {
    "name": "MB Statybos klasė",
    "code": "305903084",
    "address": "Klaipėdos r. sav., Sendvario sen., Budrikų k., Kaimynų g. 14, LT-96328",
    "vatcode": "LT100014406317"
  },
  {
    "name": "MB Stiliaus klasė",
    "code": "306668917",
    "address": "Druskininkų sav., Viečiūnų sen., Neravų k., Neravų g. 2B-4, LT-66412",
    "vatcode": "LT100016883912"
  },
  {
    "name": "UAB \"A klasė plius\"",
    "code": "304437071",
    "address": "Vilnius, Girulių g. 10, LT-12112"
  },
  {
    "name": "UAB \"Alfa klasė\"",
    "code": "304458425",
    "address": "Vilnius, Pienių g. 2, LT-10238"
  },
  {
    "name": "UAB \"Konstrukcija \"A klasė\"",
    "code": "304063353",
    "address": "Kaunas, Pašilės g. 25, LT-51390",
    "vatcode": "LT100009697013"
  },
  {
    "name": "UAB \"Spaudos klasė\"",
    "code": "124004182",
    "address": "Vilnius, Ozo g. 4, LT-08200"
  },
  {
    "name": "UAB \"Vairavimo klasė\"",
    "code": "300126105",
    "address": "Vilnius, Dariaus ir Girėno g. 13-7, LT-02181",
    "vatcode": "LT100010382213"
  },
  {
    "name": "UAB \"Verslo klasė NT\"",
    "code": "302559607",
    "address": "Kaunas, A. Juozapavičiaus pr. 112, LT-45110"
  },
  {
    "name": "Versli klasė, MB",
    "code": "306988130",
    "address": "Anykščių r. sav., Kavarsko sen., Girelės k. 4, LT-29253"
  },
  {
    "name": "Kaišiadorių klasės tėvų fondas",
    "code": "302756608",
    "address": "Kaišiadorys, Gedimino g. 111-12, LT-56150"
  },
  {
    "name": "LIETUVOS RS 280 JACHTŲ KLASĖS ASOCIACIJA",
    "code": "302631017",
    "address": "Kaunas, Jonavos g. 196, LT-44132"
  },
  {
    "name": "Lazerių jachtų klasės asociacija",
    "code": "304423310",
    "address": "Kaišiadorių r. sav., Rumšiškės, Topolių g. 5, LT-56336"
  },
  {
    "name": "Lietuvos \"Optimist\" jachtų klasės buriuotojų asociacija",
    "code": "191922334",
    "address": "Neringa, Naglių g. 14, LT-93123"
  },
  {
    "name": "UAB \"A klasės valymas\"",
    "code": "302568047",
    "address": "Kaunas, Partizanų g. 48-5, LT-49459",
    "vatcode": "LT100005822910"
  },
  {
    "name": "UAB \"Klasės dekoras\"",
    "code": "304444888",
    "address": "Vilniaus miesto savivaldybės teritorija"
  },
  {
    "name": "UAB REKLAMOS KLASĖS GRUPĖ",
    "code": "302443385",
    "address": "Vilnius, Daugėliškio g. 32-101, LT-09300",
    "vatcode": "LT100004954819"
  }
]