[
  {
    "name": "MB \"Lumo stato\"",
    "code": "306965014",
    "address": "Kaišiadorys, Gedimino g. 73-12, LT-56124"
  },
  {
    "name": "MB LuMo prekės",
    "code": "306966995",
    "address": "Vilnius, Perkūnkiemio g. 19, LT-12120"
  },
  {
    "name": "UAB \"Lumo LT\"",
    "code": "126243761",
    "address": "Vilnius, Šaltūnų g. 4A, LT-04132",
    "vatcode": "LT262437610"
  },
  {
    "name": "UAB \"Lumo lumus\"",
    "code": "303237356",
    "address": "Vilnius, Svajos g. 20, LT-11318"
  },
  {
    "name": "UAB \"Lumo production\"",
    "code": "302669879",
    "address": "Vilnius, Šaltūnų g. 4A, LT-04132"
  },
  {
    "name": "VšĮ \"Lumo\" studija",
    "code": "304402889",
    "address": "Kaunas, Kuršių g. 7-18, LT-48107",
    "vatcode": "LT100012380218"
  },
  {
    "name": "UAB \"Lumoforta\"",
    "code": "302797804",
    "address": "Vilnius, Santariškių g. 75-34, LT-08457",
    "vatcode": "LT100007066610"
  },
  {
    "name": "MB Lumoni",
    "code": "305552176",
    "address": "Kaunas, Vandžiogalos pl. 8-48, LT-47441"
  },
  {
    "name": "UAB Lumont",
    "code": "306372918",
    "address": "Palanga, Kęstučio g. 32, LT-00215",
    "vatcode": "LT100016174111"
  },
  {
    "name": "MB \"Lumos Production\"",
    "code": "306671849",
    "address": "Vilnius, V. Nagevičiaus g. 3, LT-08237"
  },
  {
    "name": "MB \"Lumos electricity\"",
    "code": "302882998",
    "address": "Kaunas, Europos pr. 122, LT-46351"
  },
  {
    "name": "MB \"Lumos projektas\"",
    "code": "306178799",
    "address": "Klaipėda, H. Manto g. 76, LT-92222",
    "vatcode": "LT100015933513"
  },
  {
    "name": "MB \"Lumos studija\"",
    "code": "306686534",
    "address": "Klaipėdos r. sav., Vėžaičiai, Jokulių g. 21, LT-96210"
  },
  {
    "name": "MB \"Lumostera\"",
    "code": "305928828",
    "address": "Kauno r. sav., Lapių sen., Tauralaukio k., Aušros g. 4, LT-54415"
  }
]