[
  {
    "name": "Futbolo klubas \"Mamukai\"",
    "code": "305635070",
    "address": "Šiauliai, Merkinės g. 25A, LT-76139"
  },
  {
    "name": "Mažoji bendrija \"Mamule\"",
    "code": "306667306",
    "address": "Kaunas, Ašigalio g. 57-29, LT-49226"
  },
  {
    "name": "MB Mamuno",
    "code": "305922889",
    "address": "Rokiškio r. sav., Panemunėlio sen., Vilių k. 7A, LT-42330"
  },
  {
    "name": "Mamur, UAB",
    "code": "305906746",
    "address": "Vilnius, Girulių g. 10, LT-12112"
  },
  {
    "name": "MB Mamus",
    "code": "306156272",
    "address": "Kaunas, Baltų pr. 159-23, LT-47122"
  },
  {
    "name": "MB \"Maži mamutai\"",
    "code": "304835470",
    "address": "Vilnius, Pagubės Sodų 13-oji g. 13, LT-14285",
    "vatcode": "LT100016860610"
  },
  {
    "name": "MB Mamutas",
    "code": "305619707",
    "address": "Vilnius, Prūsų g. 8-34, LT-02154"
  },
  {
    "name": "UAB \"Mano mamutas\"",
    "code": "303223883",
    "address": "Vilniaus miesto savivaldybės teritorija"
  },
  {
    "name": "MB \"Mamuto darbai\"",
    "code": "306369651",
    "address": "Kauno r. sav., Samylų sen., Dubravų k., Pušynėlio al. 4, LT-53174"
  },
  {
    "name": "UAB \"Mamuto namai\"",
    "code": "304142466",
    "address": "Vilnius, Deltuvos g. 31-121, LT-08100",
    "vatcode": "LT100009812511"
  },
  {
    "name": "UAB \"Mamuto tech\"",
    "code": "306970214",
    "address": "Vilnius, Valdemaro Čarneckio g. 7B, LT-11311",
    "vatcode": "LT100017128618"
  },
  {
    "name": "MB \"Rožinė mamutė\"",
    "code": "306112945",
    "address": "Panevėžys, J. Zikaro g. 28A, LT-35220"
  },
  {
    "name": "MB \"Mamučiai ir Co\"",
    "code": "305093940",
    "address": "Panevėžio r. sav., Panevėžio sen., Molainių k., Žalioji g. 15A, LT-37175"
  }
]