[
  {
    "name": "G. Miciaus komercinė įmonė",
    "code": "163287187",
    "address": "Gargždai, Vasario 16-osios g. 45, LT-96119",
    "vatcode": "LT632871811"
  },
  {
    "name": "R. Miciulevičiaus personalinė įmonė",
    "code": "165198196",
    "address": "Lazdijų r. sav., Kapčiamiestis, Taikos g. 16, LT-67313"
  },
  {
    "name": "Birutės Miciulevičienės įmonė",
    "code": "135265283",
    "address": "Kauno r. sav., Samylų sen., Gervėnupio k., Suopių g. 1, LT-53163",
    "vatcode": "LT100002439419"
  },
  {
    "name": "MB Micius media",
    "code": "306641158",
    "address": "Kaunas, Ukmergės g. 12-23, LT-49407"
  },
  {
    "name": "G. Miciūnienės personalinė įmonė",
    "code": "124843736",
    "address": "Vilnius, Ramybės g. 4, LT-02103"
  }
]