[
  {
    "name": "MB \"Tony Night House\"",
    "code": "306596649",
    "address": "Klaipėda, Vėluvos g. 12, LT-92196"
  },
  {
    "name": "UAB Day n Night kebabai",
    "code": "306338734",
    "address": "Vilnius, Mūrinės Vokės g. 7-3, LT-25140"
  },
  {
    "name": "Automobilių klubas \"NightBirdsMažeike\"",
    "code": "306967353",
    "address": "Mažeikių r. sav., Sedos sen., Nausodės k., Dariaus ir Girėno g. 107, LT-89385"
  },
  {
    "name": "MB \"NightCat Studios\"",
    "code": "306983464",
    "address": "Vilnius, Darbininkų g. 16-29, LT-02170"
  },
  {
    "name": "NIGHTJAR FINANCE CO. atstovybė",
    "code": "304138457",
    "address": "Vilniaus miesto savivaldybės teritorija"
  },
  {
    "name": "MB Nightout",
    "code": "306075219",
    "address": "Vilnius, Visorių g. 6-84, LT-08300",
    "vatcode": "LT100016128410"
  },
  {
    "name": "Quiet Nights, MB",
    "code": "306730849",
    "address": "Vilnius, Lazdynėlių g. 16-42, LT-04125"
  },
  {
    "name": "Viešoji įstaiga \"Four Nights Productions\"",
    "code": "306823869",
    "address": "Vilnius, Turniškių g. 13A, LT-10104"
  },
  {
    "name": "Nighttown, MB",
    "code": "306267721",
    "address": "Vilnius, Panerių g. 41A-101, LT-03202"
  }
]