[
  {
    "name": "MB \"PINA SERVICE\"",
    "code": "306191387",
    "address": "Vilniaus r. sav., Zujūnų sen., Geležių k., Vanagų g. 12-2, LT-14176"
  },
  {
    "name": "R. Pinaičio individuali įmonė",
    "code": "158299362",
    "address": "Jurbarko r. sav., Girdžių sen., Girdžių k., Ateities g. 5, LT-74253",
    "vatcode": "LT582993610"
  },
  {
    "name": "MB \"Pinakra\"",
    "code": "305161658",
    "address": "Vilniaus r. sav., Dūkštų sen., Rusėnų k. 5, LT-14221"
  },
  {
    "name": "MB \"Pinara\"",
    "code": "305132891",
    "address": "Kaunas, Bivylių g. 211-1, LT-47250"
  },
  {
    "name": "Daugiabučių namų savininkų bendrija \"Pinavija\"",
    "code": "141897138",
    "address": "Klaipėda, Laukininkų g. 3-21, LT-95189"
  },
  {
    "name": "MB \"Auksinė Pinavija\"",
    "code": "303044930",
    "address": "Klaipėda, Šaulių g. 8-28, LT-92137",
    "vatcode": "LT100008324911"
  },
  {
    "name": "VšĮ šokių studija \"Pinavija\"",
    "code": "303413879",
    "address": "Vilnius, Vydūno g. 18-53, LT-06205"
  },
  {
    "name": "Pinavijų gatvės bendrija",
    "code": "305257507",
    "address": "Kauno r. sav., Alšėnų sen., Jonučių k., Pinavijų g. 18, LT-53317"
  }
]