[
  {
    "name": "VIEŠIEJI INTERNETO PRIEIGOS TAŠKAI (VIPT)",
    "code": "300618195",
    "address": "Vilnius, S. Žukausko g. 18-30, LT-08234"
  },
  {
    "name": "UAB \"Viptecha\"",
    "code": "305835690",
    "address": "Kaunas, Chemijos g. 27C-62, LT-51332",
    "vatcode": "LT100015118912"
  },
  {
    "name": "UAB VIPTELA",
    "code": "305625553",
    "address": "Alytus, V. Krėvės g. 19, LT-62145"
  },
  {
    "name": "UAB \"Viptera\"",
    "code": "303468975",
    "address": "Vilnius, Laisvės pr. 60, LT-05120"
  },
  {
    "name": "UAB \"Viptona\"",
    "code": "305260567",
    "address": "Vilniaus r. sav., Bezdonių sen., Arvydų k., Liepų g. 47, LT-15204"
  },
  {
    "name": "MB VIPTOURIST",
    "code": "306083881",
    "address": "Vilnius, Kalvarijų g. 125, LT-08221"
  },
  {
    "name": "UAB Viptrans",
    "code": "306978435",
    "address": "Vilniaus r. sav., Avižienių sen., Riešės k., Bajorų g. 9, LT-14265"
  },
  {
    "name": "UAB \"Viptransit\"",
    "code": "302624898",
    "address": "Vilniaus r. sav., Marijampolio sen., Marijampolio k., Gamyklos g. 11, LT-13210",
    "vatcode": "LT100006122215"
  },
  {
    "name": "IĮ \"Vipturas\"",
    "code": "186443186",
    "address": "Vilniaus r. sav., Lavoriškių sen., Lavoriškių k., Kranto g. 2, LT-15232",
    "vatcode": "LT864431811"
  }
]