[
  {
    "name": "Uždaroji akcinė bendrovė \"VYTUKAI\"",
    "code": "124281934",
    "address": "Vilnius, Žirmūnų g. 3-32, LT-09101",
    "vatcode": "LT242819314"
  },
  {
    "name": "MB \"Vytula\"",
    "code": "305038036",
    "address": "Šiaulių r. sav., Kužiai, Statybininkų g. 16-25, LT-80266",
    "vatcode": "LT100012212116"
  },
  {
    "name": "UAB \"Vyturas\"",
    "code": "305669927",
    "address": "Kaunas, S. Žukausko g. 35-2, LT-49248"
  },
  {
    "name": "Rėkyvos seniūnijos bendruomenė \"Vyturiai\"",
    "code": "302734743",
    "address": "Šiauliai, Vyturio Sodų 7-oji g. 25, LT-79200"
  },
  {
    "name": "Dariaus Vyturio įmonė",
    "code": "174442895",
    "address": "Šakių r. sav., Gelgaudiškio sen., Voniškių k."
  },
  {
    "name": "Daugiabučio namo savininkų bendrija \"Vyturio g. 2, Klaipėda, savininkų bendrija\"",
    "code": "306964407",
    "address": "Klaipėda, Vyturio g. 2, LT-95181"
  },
  {
    "name": "Kauno \"Vyturio\" gimnazija",
    "code": "190136887",
    "address": "Kaunas, Taikos pr. 51, LT-50428"
  },
  {
    "name": "Klaipėdos \"Vyturio\" progimnazija",
    "code": "190438615",
    "address": "Klaipėda, Laukininkų g. 30, LT-95149"
  },
  {
    "name": "Mažeikių \"Vyturio\" pradinė mokykla",
    "code": "191814796",
    "address": "Mažeikiai, Sodų g. 14, LT-89116"
  },
  {
    "name": "Panevėžio \"Vyturio\" progimnazija",
    "code": "190423499",
    "address": "Panevėžys, Vasario 16-osios g. 40, LT-35168"
  },
  {
    "name": "S. Vyturio įmonė",
    "code": "159867191",
    "address": "Kauno r. sav., Raudondvario sen., Raudondvario k., Vyturių g. 16, LT-54118"
  },
  {
    "name": "Uždaroji akcinė bendrovė \"VYTURIO GIESMĖ\"",
    "code": "242008450",
    "address": "Klaipėda, Laukininkų g. 17, LT-95146"
  },
  {
    "name": "Uždaroji akcinė bendrovė \"VYTURIO\" PAUKŠTYNAS",
    "code": "142171343",
    "address": "Klaipėda, K. Donelaičio g. 19, LT-92141"
  },
  {
    "name": "Vilniaus \"Vyturio\" pradinė mokykla",
    "code": "190009167",
    "address": "Vilnius, Taikos g. 189, LT-05209"
  },
  {
    "name": "Vyturio Jaručio leidykla \"Strofa\"",
    "code": "135129080",
    "address": "Vilnius, Šv. Ignoto g. 5-251"
  },
  {
    "name": "VšĮ \"Vyturio leidyba\"",
    "code": "304914074",
    "address": "Vilnius, Žirmūnų g. 32E-26, LT-09228"
  },
  {
    "name": "Daugiabučio namo savininkų bendrija \"Vyturita\"",
    "code": "303478446",
    "address": "Klaipėda, Vyturio g. 23, LT-95183"
  },
  {
    "name": "UAB Vyturiukas Group",
    "code": "306218795",
    "address": "Kaunas, V. Bičiūno g. 33-1, LT-47240",
    "vatcode": "LT100015601516"
  },
  {
    "name": "VšĮ \"Vyturiukas LT\"",
    "code": "304377845",
    "address": "Kaunas, V. Bičiūno g. 33-1, LT-47240",
    "vatcode": "LT100010636118"
  },
  {
    "name": "Asociacija \"Vyturių gatvės bendruomenė\"",
    "code": "302844047",
    "address": "Šiaulių r. sav., Šiaulių kaimiškoji sen., Raizgių k., Vyturių g. 11, LT-80184"
  },
  {
    "name": "Daugiabučio namo savininkų bendrija \"Vyturių 2\"",
    "code": "160434778",
    "address": "Kauno r. sav., Raudondvario sen., Raudondvario k., Vyturių g. 2, LT-54124"
  },
  {
    "name": "Daugiabučio namo savininkų bendrija \"Vyturių 2a\"",
    "code": "160434810",
    "address": "Kauno r. sav., Raudondvario sen., Raudondvario k., Vyturių g. 2A, LT-54124"
  },
  {
    "name": "Utenos Vyturių progimnazija",
    "code": "190182354",
    "address": "Utena, Sėlių g. 45, LT-28203"
  },
  {
    "name": "Biržų rajono sodininkų bendrija \"Vyturys\"",
    "code": "190964992",
    "address": "Biržai, Respublikos g. 58-12, LT-41143"
  },
  {
    "name": "Daugiabučio namo savininkų bendrija \"VYTURYS\"",
    "code": "141796826",
    "address": "Klaipėda, Statybininkų pr. 28, LT-94228"
  },
  {
    "name": "Daugiabučio namo savininkų bendrija \"Vyturys\"",
    "code": "173244490",
    "address": "Rokiškis, Panevėžio g. 20-22, LT-42156"
  },
  {
    "name": "Garažų statybos ir eksploatavimo bendrija \"Vyturys\"",
    "code": "168938513",
    "address": "Panevėžio r. sav., Velžio sen., Staniūnų k."
  },
  {
    "name": "Kaišiadorių rajono sodininkų bendrija \"Vyturys\"",
    "code": "301170599",
    "address": "Kaunas, Šiaurės pr. 6-34, LT-49156"
  },
  {
    "name": "Lazdijų miesto pedagogų klubas \"Vyturys\"",
    "code": "300093438",
    "address": "Lazdijai, Senamiesčio g. 8, LT-67105"
  },
  {
    "name": "Mišrus choras \"Vyturys\"",
    "code": "301566787",
    "address": "Ukmergė, Kauno g. 8, LT-20114"
  },
  {
    "name": "Pasvalio rajono sodininkų bendrija \"Vyturys\"",
    "code": "303187259",
    "address": "Pasvalys, Žemdirbių g. 5, LT-39107"
  },
  {
    "name": "SODININKŲ BENDRIJA \"VYTURYS\"",
    "code": "145662155",
    "address": "Šiauliai, J. Basanavičiaus g. 17, LT-76234"
  },
  {
    "name": "Sodininkų bendrija \"VYTURYS\"",
    "code": "191037995",
    "address": "Kėdainių r. sav., Kėdainių miesto sen., Justinavos k."
  },
  {
    "name": "Sodininkų bendrija \"Vyturys 1\"",
    "code": "306161376",
    "address": "Vilkaviškis, Vanagų g. 12, LT-70177"
  },
  {
    "name": "Sodininkų bendrija \"Vyturys 2\"",
    "code": "302527698",
    "address": "Vilkaviškis, Birutės g. 27, LT-70145"
  },
  {
    "name": "Sodininkų bendrija \"Vyturys\"",
    "code": "300577663",
    "address": "Ukmergė, Kauno g. 2-10, LT-20114"
  },
  {
    "name": "UAB \"Šiaulių vyturys\"",
    "code": "301144711",
    "address": "Šiauliai, Daubos g. 1C, LT-78150",
    "vatcode": "LT100005000818"
  },
  {
    "name": "Uždaroji akcinė bendrovė \"PAMARIO VYTURYS\"",
    "code": "140620031",
    "address": "Klaipėda, Laukininkų g. 19, LT-95146",
    "vatcode": "LT406200314"
  },
  {
    "name": "Uždaroji akcinė bendrovė \"VYTURYS\"",
    "code": "140548023",
    "address": "Klaipėda, K. Donelaičio g. 19, LT-92141",
    "vatcode": "LT405480219"
  },
  {
    "name": "Molėtų \"Vyturėlio\" vaikų lopšelis-darželis",
    "code": "191231719",
    "address": "Molėtai, Vilniaus g. 57, LT-33140"
  },
  {
    "name": "Alytaus lopšelis-darželis \"Vyturėlis\"",
    "code": "191054044",
    "address": "Alytus, Miklusėnų g. 38A, LT-62333"
  },
  {
    "name": "Birštono vaikų lopšelis-darželis \"Vyturėlis\"",
    "code": "190025367",
    "address": "Birštonas, Vilniaus g. 14, LT-59214"
  },
  {
    "name": "Biržų mokykla-darželis \"Vyturėlis\"",
    "code": "290533950",
    "address": "Biržai, Vilniaus g. 109, LT-41115"
  },
  {
    "name": "Daugiabučio namo savininkų bendrija \"Vyturėlis\"",
    "code": "184250893",
    "address": "Utena, Aukštakalnio g. 80, LT-28176"
  },
  {
    "name": "Joniškio vaikų darželis \"Vyturėlis\"",
    "code": "190550347",
    "address": "Joniškis, Melioratorių a. 14-1, LT-84173"
  },
  {
    "name": "Kauno lopšelis-darželis \"Vyturėlis\"",
    "code": "191643256",
    "address": "Kaunas, Kalniečių g. 214, LT-49409"
  },
  {
    "name": "Kauno r. Raudondvario lopšelis-darželis \"Vyturėlis\"",
    "code": "191631097",
    "address": "Kauno r. sav., Raudondvario sen., Raudondvario k., Vyturių g. 2B, LT-54124"
  },
  {
    "name": "Klaipėdos lopšelis-darželis \"Vyturėlis\"",
    "code": "190436183",
    "address": "Klaipėda, Vyturio g. 17, LT-95186"
  },
  {
    "name": "Kėdainių lopšelis-darželis \"Vyturėlis\"",
    "code": "191018532",
    "address": "Kėdainiai, Josvainių g. 53, LT-57266"
  },
  {
    "name": "Lazdijų mokykla-darželis \"Vyturėlis\"",
    "code": "290607190",
    "address": "Lazdijai, Senamiesčio g. 8, LT-67105"
  },
  {
    "name": "Pakruojo vaikų lopšelis-darželis \"Vyturėlis\"",
    "code": "190061783",
    "address": "Pakruojis, Mindaugo g. 8, LT-83136"
  },
  {
    "name": "Panevėžio lopšelis-darželis \"Vyturėlis\"",
    "code": "190375823",
    "address": "Panevėžys, Žvaigždžių g. 24, LT-37113"
  },
  {
    "name": "Plungės lopšelis-darželis \"Vyturėlis\"",
    "code": "191128950",
    "address": "Plungė, Birutės g. 22B, LT-90113"
  },
  {
    "name": "Sodininkų bendrija \"Sodo vyturėlis\"",
    "code": "300105036",
    "address": "Utenos r. sav., Leliūnų sen., Jasonių k., Pempių g. 1, LT-28103"
  },
  {
    "name": "Sodininkų bendrija \"Vyturėlis\"",
    "code": "190949175",
    "address": "Alytaus r. sav., Alovės sen., Jurkionių k."
  },
  {
    "name": "Ukmergės specialiojo ugdymo centro \"Vyturėlis\" darbuotojų profesinė sąjunga",
    "code": "183243579",
    "address": "Ukmergė, Veterinarijos g. 5, LT-20183"
  },
  {
    "name": "Zarasų rajono sodininkų bendrija \"Vyturėlis\"",
    "code": "190853134",
    "address": "Zarasai, Savanorių g."
  },
  {
    "name": "Šalčininkų lopšelio-darželio \"Vyturėlis\" darbuotojų profesinė sąjunga",
    "code": "304194363",
    "address": "Vilnius, Vandentiekio g. 56, LT-03152"
  },
  {
    "name": "Šalčininkų lopšelis-darželis \"Vyturėlis\"",
    "code": "191408945",
    "address": "Šalčininkai, J. Sniadeckio g. 15, LT-17108"
  },
  {
    "name": "Švenčionių r. Švenčionėlių lopšelis-darželis \"Vyturėlis\"",
    "code": "190503810",
    "address": "Švenčionių r. sav., Švenčionėliai, Ateities g. 50, LT-18215"
  },
  {
    "name": "Tatjanos Vytuvienės individuali įmonė",
    "code": "302769420",
    "address": "Šilutė, Jaunimo al. 5-60, LT-99118"
  }
]