[
  {
    "name": "UAB ĮRA Servisas",
    "code": "306104927",
    "address": "Klaipėdos r. sav., Sendvario sen., Trušelių k., Viliūnų g. 24, LT-92440",
    "vatcode": "LT100015078314"
  },
  {
    "name": "Bendra Lietuvos ir Vokietijos įmonė uždaroji akcinė bendrovė \"MBR PARDUOTUVIŲ IR RESTORANŲ ĮRANGA\"",
    "code": "110451974",
    "address": "Vilnius, Kirtimų g. 49B, LT-02244",
    "vatcode": "LT104519716"
  },
  {
    "name": "MB \"Domo programinė įranga\"",
    "code": "304296980",
    "address": "Kaunas, Kęstučio g. 55-7, LT-44306",
    "vatcode": "LT100012293617"
  },
  {
    "name": "MB \"Lauko žaidimų įranga\"",
    "code": "304894013",
    "address": "Alytaus r. sav., Daugai, Ežero g. 19-3, LT-64137"
  },
  {
    "name": "MB \"Luko prekybinė šaldymo įranga\"",
    "code": "304389370",
    "address": "Šilutė, Vytauto g. 29-31, LT-99178",
    "vatcode": "LT100010394318"
  },
  {
    "name": "MB \"Renginių įranga\"",
    "code": "303842896",
    "address": "Vilniaus r. sav., Rukainių sen., Užukenės k., Užukenės g. 3, LT-13183",
    "vatcode": "LT100009322214"
  },
  {
    "name": "MB \"Restoranų įranga\"",
    "code": "303105707",
    "address": "Vilnius, Vito Gerulaičio g. 1-59, LT-08200",
    "vatcode": "LT100007902015"
  },
  {
    "name": "MB \"Sekimo įranga LT\"",
    "code": "304887894",
    "address": "Kauno r. sav., Babtų sen., Naujatriobių k., Kalno g. 21, LT-54100"
  },
  {
    "name": "MB \"Virtuvės įranga profesionalams\"",
    "code": "305053515",
    "address": "Vilnius, Juozo Balčikonio g. 3-48, LT-08247",
    "vatcode": "LT100012278613"
  },
  {
    "name": "MB \"Šviesos įranga\"",
    "code": "304803921",
    "address": "Kaunas, V. Krėvės pr. 81-519, LT-50362",
    "vatcode": "LT100014453510"
  },
  {
    "name": "MB \"Žemaitijos krašto programinė įranga ir jos priežiūra\"",
    "code": "303234196",
    "address": "Klaipėda, Taikos pr. 24-13, LT-91222"
  },
  {
    "name": "MB Salonų įranga",
    "code": "305755671",
    "address": "Kaunas, Partizanų g. 50-99, LT-49459"
  },
  {
    "name": "MB Slaugos įranga",
    "code": "305682369",
    "address": "Vilnius, Statybininkų g. 1-68, LT-03205"
  },
  {
    "name": "UAB \"Baltijos įranga\"",
    "code": "304457750",
    "address": "Vilnius, Svajonių g. 10-5, LT-10103",
    "vatcode": "LT100012159217"
  },
  {
    "name": "UAB \"ELEKTROS ĮRANGA\"",
    "code": "110750930",
    "address": "Panevėžys, Tinklų g. 29A-3, LT-35115",
    "vatcode": "LT107509314"
  },
  {
    "name": "UAB \"Kemperių įranga\"",
    "code": "305702067",
    "address": "Šilutės r. sav., Vainutas, Galnės g. 8, LT-99432",
    "vatcode": "LT100014139617"
  },
  {
    "name": "UAB \"MEDŽIO TECHNOLOGINĖ ĮRANGA\"",
    "code": "169291979",
    "address": "Pasvalys, Mūšos g. 22D, LT-39104",
    "vatcode": "LT692919716"
  },
  {
    "name": "UAB \"Medicinos įranga\"",
    "code": "304701254",
    "address": "Kauno r. sav., Ringaudų sen., Ringaudų k., Žalgirio g. 20-1, LT-53331",
    "vatcode": "LT100011332818"
  },
  {
    "name": "UAB \"Plastinės chirurgijos įranga\"",
    "code": "305189643",
    "address": "Kaunas, Taikos pr. 141, LT-51132",
    "vatcode": "LT100012445115"
  },
  {
    "name": "UAB \"Pramogų įranga\"",
    "code": "306638094",
    "address": "Kaunas, J. Biliūno g. 7, LT-46379",
    "vatcode": "LT100016568617"
  },
  {
    "name": "UAB \"RD Medicininė įranga\"",
    "code": "304953305",
    "address": "Kaunas, Sporto g. 3, LT-44221"
  },
  {
    "name": "UAB \"Sandėliavimo įranga\"",
    "code": "304089832",
    "address": "Mažeikių r. sav., Židikai, Viliotės g. 4, LT-89442",
    "vatcode": "LT100009666911"
  },
  {
    "name": "UAB \"Įranga grožiui\"",
    "code": "305480143",
    "address": "Kauno r. sav., Lapių sen., Ginėnų k., Ginėnų g. 23, LT-54430"
  },
  {
    "name": "UAB \"Įranga technologijos\"",
    "code": "304415370",
    "address": "Elektrėnų sav., Vievis, Ateities g. 3, LT-21366",
    "vatcode": "LT100010636612"
  },
  {
    "name": "UAB \"Įranga verslui\"",
    "code": "302536697",
    "address": "Vilnius, Pajautos g. 11-5, LT-06203",
    "vatcode": "LT100005607319"
  },
  {
    "name": "UAB \"Įranga\"",
    "code": "304462480",
    "address": "Marijampolės sav., Marijampolės sen., Skaisčiūnų k., Tarpučių g. 216-1, LT-69338",
    "vatcode": "LT100010738018"
  },
  {
    "name": "UAB \"Šildymo įranga\"",
    "code": "304945493",
    "address": "Kauno r. sav., Vilkija, Kauno g. 75, LT-54228"
  },
  {
    "name": "UAB \"Žaidimų aikštelių įranga\"",
    "code": "304210682",
    "address": "Alytaus r. sav., Daugų sen., Salos k., Gandrų g. 3, LT-64136",
    "vatcode": "LT100010205819"
  },
  {
    "name": "UAB \"Žvėrininkystės įranga\"",
    "code": "163663650",
    "address": "Klaipėdos r. sav., Kretingalės sen., Kunkių k., Karklų g. 36, LT-92382",
    "vatcode": "LT636636515"
  },
  {
    "name": "UAB Medicinos grupės įranga",
    "code": "305689488",
    "address": "Kaunas, Č. Sasnausko g. 19, LT-44149",
    "vatcode": "LT100013953214"
  },
  {
    "name": "Uždaroji akcinė bendrovė \"Apskaitos įranga\"",
    "code": "123756470",
    "address": "Vilnius, A. Goštauto g. 8-109, LT-01108"
  },
  {
    "name": "Uždaroji akcinė bendrovė \"Arevitos įranga\"",
    "code": "135226476",
    "address": "Kaunas, J. Grušo g. 5-4, LT-48266",
    "vatcode": "LT352264716"
  },
  {
    "name": "Uždaroji akcinė bendrovė \"DETALĖS IR TECHNOLOGINĖ ĮRANGA\"",
    "code": "123231024",
    "address": "Vilnius, Lakūnų g. 3, LT-09108",
    "vatcode": "LT232310219"
  },
  {
    "name": "Uždaroji akcinė bendrovė \"Kavinių įranga\"",
    "code": "181264592",
    "address": "Trakų r. sav., Lentvaris, Fabriko g. 6, LT-25121"
  },
  {
    "name": "Uždaroji akcinė bendrovė \"Metalo įranga\"",
    "code": "120185237",
    "address": "Vilnius, Metalo g. 10, LT-02190",
    "vatcode": "LT201852314"
  },
  {
    "name": "Uždaroji akcinė bendrovė \"PROTOTECHNIKOS ĮRANGA\"",
    "code": "123547225",
    "address": "Vilnius, Žemaitės g. 26, LT-03201",
    "vatcode": "LT235472219"
  },
  {
    "name": "Uždaroji akcinė bendrovė \"Sisteminio administravimo technologijos ir įranga\"",
    "code": "126419558",
    "address": "Vilnius, Antakalnio g. 66-13, LT-10300",
    "vatcode": "LT264195515"
  },
  {
    "name": "Virtuvinė įranga, MB",
    "code": "306219349",
    "address": "Vilnius, Perkūnkiemio g. 13-91, LT-12114",
    "vatcode": "LT100015678110"
  },
  {
    "name": "UAB \"Įrangesa\"",
    "code": "303371234",
    "address": "Šiauliai, Dainavos tak. 3B-31, LT-77146",
    "vatcode": "LT100009321317"
  },
  {
    "name": "Bendrojo naudojimo inžinerinių tinklų ir įrangos eksploatavimo bendrija \"Žaizdrių EKV\"",
    "code": "281624290",
    "address": "Trakai, Birutės g. 42, LT-21114"
  },
  {
    "name": "E. Pečiūros radioelektroninės įrangos firma \"PERKOM\"",
    "code": "121375727",
    "address": "Vilnius, M. Daukšos g. 10-3, LT-02102"
  },
  {
    "name": "LIETUVOS MEDICININĖS ĮRANGOS GAMINTOJŲ ASOCIACIJA",
    "code": "302523290",
    "address": "Vilnius, Geležinio Vilko g. 18A, LT-08126"
  },
  {
    "name": "Lietuvos automobilių dujų įrangos montuotojų asociacija \"Autoekologija\"",
    "code": "135588678",
    "address": "Alytus, Santaikos g. 26G, LT-62123"
  },
  {
    "name": "MB \"Programinės įrangos sprendimai\"",
    "code": "305171894",
    "address": "Šiauliai, Lyros g. 5-98, LT-78287"
  },
  {
    "name": "MB \"Programinės įrangos testavimo sprendimai\"",
    "code": "305393667",
    "address": "Kaunas, Taikos pr. 41-69, LT-50225"
  },
  {
    "name": "MB \"Įrangos projektavimas\"",
    "code": "304897721",
    "address": "Alytus, Statybininkų g. 25-52, LT-63408"
  },
  {
    "name": "MB Programinės įrangos gamykla",
    "code": "304737624",
    "address": "Vilnius, Architektų g. 36-1, LT-04121"
  },
  {
    "name": "MB Virtuvinės įrangos servisas",
    "code": "306768351",
    "address": "Vilniaus r. sav., Mickūnai, Darbininkų g. 1, LT-13114"
  },
  {
    "name": "MB Įrangos prekyba",
    "code": "306163352",
    "address": "Vilnius, Girulių g. 10, LT-12112"
  },
  {
    "name": "PROGRAMINĖS ĮRANGOS TESTUOTOJŲ ASOCIACIJA",
    "code": "306352716",
    "address": "Vilnius, Juozo Rutkausko g. 6, LT-05132"
  },
  {
    "name": "Ričardo Cimalansko programinės įrangos sudarymo kompiuteriams įmonė \"Plius minus\"",
    "code": "157535596",
    "address": "Joniškis, Malūno g. 27, LT-84157",
    "vatcode": "LT575355917"
  },
  {
    "name": "STATYBOS MECHANIZMŲ IR ĮRANGOS NUOMOTOJŲ ASOCIACIJA",
    "code": "134811726",
    "address": "Vilnius, Metalo g. 9, LT-02190"
  },
  {
    "name": "UAB ELEKTROSAUGOS ĮRANGOS CENTRAS",
    "code": "145668222",
    "address": "Šiauliai, Ežero g. 8, LT-77141",
    "vatcode": "LT456682219"
  },
  {
    "name": "Uždaroji akcinė bendrovė \"ĮRANGOS DETALIŲ SISTEMA\"",
    "code": "124446510",
    "address": "Vilnius, Kirtimų g. 49B, LT-02244",
    "vatcode": "LT244465113"
  },
  {
    "name": "Įrangos valdymo sprendimai, MB",
    "code": "306620203",
    "address": "Vilnius, Kareivių g. 11B, LT-09133"
  },
  {
    "name": "MB \"Raimio įrankiai\"",
    "code": "306075621",
    "address": "Alytus, Gudalaukio g. 22, LT-62445",
    "vatcode": "LT100015145819"
  },
  {
    "name": "MB Įrankiai pramonei",
    "code": "306109867",
    "address": "Kaunas, Savanorių pr. 172, LT-44149",
    "vatcode": "LT100015751317"
  },
  {
    "name": "UAB \"Guoliai ir įrankiai\"",
    "code": "300500318",
    "address": "Utena, Tulpių g. 8, LT-28247",
    "vatcode": "LT100001914319"
  },
  {
    "name": "UAB \"LIUDO ĮRANKIAI\"",
    "code": "134008955",
    "address": "Kaunas, Darbo g. 42, LT-52102",
    "vatcode": "LT340089515"
  },
  {
    "name": "UAB \"Rimanto įrankiai\"",
    "code": "305646266",
    "address": "Panevėžys, Tinklų g. 25A, LT-35115",
    "vatcode": "LT100013501115"
  },
  {
    "name": "UAB \"Visi įrankiai\"",
    "code": "123894496",
    "address": "Vilnius, Liepkalnio g. 68, LT-02120",
    "vatcode": "LT238944917"
  },
  {
    "name": "UAB \"ĮRANKIAI VISIEMS\" IR KO",
    "code": "148436752",
    "address": "Panevėžys, Paliūniškio g. 13, LT-35114",
    "vatcode": "LT484367515"
  },
  {
    "name": "UAB \"Įrankiai meistrams\"",
    "code": "304720920",
    "address": "Vilnius, Girulių g. 10, LT-12112"
  },
  {
    "name": "UAB \"Įrankiai visiems\"",
    "code": "147762236",
    "address": "Panevėžys, Paliūniškio g. 13, LT-35114",
    "vatcode": "LT477622314"
  },
  {
    "name": "UAB \"Įrankiai.lt\"",
    "code": "302561679",
    "address": "Kaunas, Islandijos pl. 161-2, LT-49120",
    "vatcode": "LT100005746714"
  },
  {
    "name": "UŽDAROJI AKCINĖ BENDROVĖ \"ĮRANKIAI\"",
    "code": "144903354",
    "address": "Šiauliai, Sodo g. 35D, LT-76180",
    "vatcode": "LT449033515"
  },
  {
    "name": "Valentinos Krochmal firma \"Įrankiai Jums\"",
    "code": "123358534",
    "address": "Vilnius, Sausio 13-osios g. 33-106, LT-04348"
  },
  {
    "name": "MB Įrankinė",
    "code": "306140599",
    "address": "Marijampolė, Vokiečių g. 5-4, LT-68137",
    "vatcode": "LT100015296719"
  },
  {
    "name": "MB \"Efektyvus įrankis\"",
    "code": "305879612",
    "address": "Jurbarkas, Kauno g. 36-47A, LT-74125"
  },
  {
    "name": "Mažoji bendrija Auto įrankis",
    "code": "306675986",
    "address": "Vilnius, Architektų g. 91-29, LT-04207"
  },
  {
    "name": "UAB \"Tavo įrankis\"",
    "code": "302863492",
    "address": "Joniškis, Vilniaus g. 2, LT-84147",
    "vatcode": "LT100007137219"
  },
  {
    "name": "UAB \"Įrankis.lt\"",
    "code": "304105382",
    "address": "Kaunas, Raudondvario pl. 150B, LT-47174",
    "vatcode": "LT100009762118"
  },
  {
    "name": "MB \"Įrankių dėžutė\"",
    "code": "304754075",
    "address": "Panevėžys, Molainių g. 82-11, LT-37152"
  },
  {
    "name": "MB \"Įrankių dėžė\"",
    "code": "304421494",
    "address": "Švenčionių r. sav., Švenčionėliai, Geležinkelio skg. 7-40, LT-18223"
  },
  {
    "name": "MB \"Įrankių servisas\"",
    "code": "302918280",
    "address": "Kretinga, Tiekėjų g. 43, LT-97187",
    "vatcode": "LT100015509919"
  },
  {
    "name": "MB Įrankių kodas",
    "code": "305687697",
    "address": "Klaipėdos r. sav., Sendvario sen., Klipščių k., Tulpininkų g. 2, LT-92339"
  },
  {
    "name": "UAB \"Leuko įrankių servisas\"",
    "code": "304920390",
    "address": "Vilnius, Ukmergės g. 281, LT-06318",
    "vatcode": "LT100011938512"
  },
  {
    "name": "UAB \"Įrankių ekspresas\"",
    "code": "304993883",
    "address": "Kaunas, V. Krėvės pr. 89-33, LT-50365",
    "vatcode": "LT100012468215"
  },
  {
    "name": "UAB \"Įrankių galandimas\"",
    "code": "271468220",
    "address": "Radviliškis, Maironio g. 101A, LT-82129"
  },
  {
    "name": "UAB \"Įrankių nuoma.lt\"",
    "code": "305444193",
    "address": "Kaunas, Saulės g. 39-49, LT-51362",
    "vatcode": "LT100013233719"
  },
  {
    "name": "UAB Įrankių sala",
    "code": "302602179",
    "address": "Vilnius, Račių g. 6A, LT-03156",
    "vatcode": "LT100005980611"
  },
  {
    "name": "Įrankių miestas, MB",
    "code": "306649137",
    "address": "Vilnius, Lūkesčių g. 49, LT-04125",
    "vatcode": "LT100016613616"
  },
  {
    "name": "UAB \"Įranktopas\"",
    "code": "306573593",
    "address": "Kaunas, R. Kalantos g. 102-30, LT-52349",
    "vatcode": "LT100016367616"
  },
  {
    "name": "MB Įrankynas",
    "code": "306036682",
    "address": "Vilnius, Algirdo g. 37A-10, LT-03217",
    "vatcode": "LT100015948612"
  },
  {
    "name": "MB Cirko įrašai",
    "code": "306370155",
    "address": "Kauno r. sav., Ringaudų sen., Noreikiškių k., Žaibo g. 7B, LT-53365"
  },
  {
    "name": "Ramūs įrašai VšĮ",
    "code": "305739222",
    "address": "Prienų r. sav., Stakliškių sen., Bagdoniškių k. 11, LT-59354"
  },
  {
    "name": "Uždaroji akcinė bendrovė \"GARSŲ PASAULIO ĮRAŠAI\"",
    "code": "124689779",
    "address": "Vilnius, Pamėnkalnio g. 14, LT-01114",
    "vatcode": "LT246897716"
  },
  {
    "name": "VšĮ \"Arno įrašai\"",
    "code": "305054994",
    "address": "Vilnius, P. Žadeikos g. 22-44, LT-06321"
  },
  {
    "name": "VšĮ \"Mono Stereo Įrašai\"",
    "code": "301342547",
    "address": "Vilnius, V. Grybo g. 43-9, LT-10320",
    "vatcode": "LT100003846412"
  },
  {
    "name": "MB \"Buhalterinis įrašas\"",
    "code": "304254611",
    "address": "Kauno r. sav., Ringaudų sen., Virbališkių k., Viekšnupio g. 5, LT-53458",
    "vatcode": "LT100013525911"
  },
  {
    "name": "MB \"Naujas įrašas\"",
    "code": "306060726",
    "address": "Kaunas, A. Juozapavičiaus pr. 13D-1, LT-45252",
    "vatcode": "LT100014905714"
  },
  {
    "name": "UAB \"Dvigubas įrašas\" apskaita",
    "code": "301841938",
    "address": "Marijampolė, Vasario 16-osios g. 10-48, LT-68301",
    "vatcode": "LT100004242013"
  },
  {
    "name": "Uždaroji akcinė bendrovė \"Dvigubas įrašas\"",
    "code": "151353042",
    "address": "Marijampolė, Vytauto g. 18, LT-68298",
    "vatcode": "LT513530411"
  },
  {
    "name": "UAB \"Dvigubo įrašo\" audito biuras",
    "code": "151478010",
    "address": "Marijampolė, V. Kudirkos g. 85, LT-68291"
  },
  {
    "name": "A. Greviškio garso įrašų studija \"Melodija\"",
    "code": "147276063",
    "address": "Panevėžys, Aldonos g. 7-39, LT-35229"
  },
  {
    "name": "Giedriaus Litvino garso įrašų studija",
    "code": "134126220",
    "address": "Kaunas, T. Narbuto g. 6-1"
  },
  {
    "name": "IĮ Garso įrašų studija \"Progresija\"",
    "code": "304405636",
    "address": "Marijampolės sav., Marijampolės sen., Baraginės k., Užupių g. 11, LT-69491"
  }
]